maple/__init__.py
maple/contrib/__init__.py
maple/contrib/virtual_request.py
maple/share/__init__.py
maple/share/constants.py
maple/share/log.py
maple/share/task.py
maple/share/utils.py
maple/share/proto/__init__.py
maple/share/proto/maple_pb2.py
maple/trigger/__init__.py
maple/trigger/client.py
maple/trigger/trigger.py
maple/workshop/__init__.py
maple/workshop/blueprint.py
maple/workshop/workshop.py
maple/workshop/common/__init__.py
maple/workshop/common/mixins.py
maple/workshop/master/__init__.py
maple/workshop/master/master.py
maple/workshop/worker/__init__.py
maple/workshop/worker/connection.py
maple/workshop/worker/request.py
maple/workshop/worker/worker.py
maple-4.1.6.dist-info/METADATA
maple-4.1.6.dist-info/WHEEL
maple-4.1.6.dist-info/top_level.txt
maple-4.1.6.dist-info/RECORD
