Metadata-Version: 2.1
Name: maple
Version: 4.1.6
Summary: reliable, scalable, distributed server framework
Author-email: dantezhu <zny2008@gmail.com>
License: MIT
Project-URL: Homepage, https://github.com/dantezhu/maple
Requires-Python: >=3
Requires-Dist: events
Requires-Dist: netkit
Requires-Dist: protobuf <4.0.0,>=3.9.1
Requires-Dist: setproctitle
